[
    {
        "name": "Psychedelic Electronic",
        "songs": [
            {
                "artist": "Greg Haines",
                "name": "So It Goes",
                "album": "Where We Were"
            },
            {
                "artist": "Boards of Canada",
                "name": "Reach For The Dead",
                "album": "Tomorrow's Harvest"
            },
            {
                "artist": "The Glitch Mob",
                "name": "Starve The Ego, Feed The Soul",
                "album": "Drink the Sea"
            },
            {
                "artist": "AZEL PHARA",
                "name": "Tump",
                "album": "Pump"
            },
            {
                "artist": "The Field",
                "name": "Mobilia",
                "album": "From Here We Go Sublime"
            },
            {
                "artist": "Nathan Fake",
                "name": "The Sky Was Pink",
                "album": "Drowning In A Sea Of Love"
            },
            {
                "artist": "Four Tet",
                "name": "Evening Side",
                "album": "Morning / Evening"
            },
            {
                "artist": "Chrome Sparks",
                "name": "Goddess",
                "album": "Goddess"
            },
            {
                "artist": "Burial",
                "name": "Untrue",
                "album": "Untrue"
            },
            {
                "artist": "RÜFÜS DU SOL",
                "name": "Innerbloom",
                "album": "Bloom"
            },
            {
                "artist": "Clams Casino",
                "name": "Gorilla",
                "album": "Rainforest"
            },
            {
                "artist": "Yagya",
                "name": "Rigning Einn",
                "album": "Rigning (2018)"
            },
            {
                "artist": "Aphex Twin",
                "name": "Polynomial-C",
                "album": "Xylem Tube EP"
            },
            {
                "artist": "Teebs",
                "name": "SOTM",
                "album": "E s t a r a"
            },
            {
                "artist": "Moderat",
                "name": "The Mark - Interlude",
                "album": "II"
            },
            {
                "artist": "Sasha",
                "name": "Linepulse",
                "album": "Late Night Tales presents Sasha: Scene Delete"
            },
            {
                "artist": "Boards of Canada",
                "name": "Music Is Math",
                "album": "Geogaddi"
            },
            {
                "artist": "Burial",
                "name": "Ghost Hardware",
                "album": "Untrue"
            },
            {
                "artist": "Aphex Twin",
                "name": "Xtal",
                "album": "Selected Ambient Works 85-92"
            },
            {
                "artist": "Autechre",
                "name": "VLetrmx",
                "album": "Garbage"
            },
            {
                "artist": "Teebs",
                "name": "Why Like This?",
                "album": "Ardour"
            },
            {
                "artist": "Four Tet",
                "name": "Lion - Jamie XX Remix",
                "album": "Pink Remixes"
            },
            {
                "artist": "Jon Hopkins",
                "name": "Light Through The Veins",
                "album": "Insides"
            },
            {
                "artist": "The Field",
                "name": "Everybody´s Got To Learn Sometime",
                "album": "Yesterday and Today"
            },
            {
                "artist": "Jamie xx",
                "name": "Gosh",
                "album": "In Colour"
            },
            {
                "artist": "Fatima Yamaha",
                "name": "Imaginary Lines",
                "album": "Imaginary Lines"
            },
            {
                "artist": "Moderat",
                "name": "Last Time - Jon Hopkins Remix",
                "album": "Last Time"
            },
            {
                "artist": "Oneohtrix Point Never",
                "name": "Boring Angel",
                "album": "R Plus Seven"
            },
            {
                "artist": "Vessels",
                "name": "Vertical",
                "album": "Dilate (Special Edition)"
            },
            {
                "artist": "Boards of Canada",
                "name": "Olson",
                "album": "Music Has The Right To Children"
            },
            {
                "artist": "Sasha",
                "name": "Time After Time",
                "album": "Late Night Tales presents Sasha: Scene Delete"
            },
            {
                "artist": "Haring",
                "name": "Us",
                "album": "Nowadays"
            },
            {
                "artist": "Clams Casino",
                "name": "Into the Fire - Instrumental",
                "album": "32 Levels (Deluxe)"
            },
            {
                "artist": "The Field",
                "name": "Everyday",
                "album": "From Here We Go Sublime"
            },
            {
                "artist": "Jamie xx",
                "name": "Sleep Sound",
                "album": "Girl/Sleep Sound"
            },
            {
                "artist": "Vessels",
                "name": "The Sky Was Pink",
                "album": "The Sky Was Pink"
            },
            {
                "artist": "Aphex Twin",
                "name": "Windowlicker",
                "album": "Windowlicker"
            },
            {
                "artist": "Jon Hopkins",
                "name": "Luminous Beings",
                "album": "Singularity"
            },
            {
                "artist": "Blockhead",
                "name": "The Music Scene",
                "album": "The Music Scene"
            },
            {
                "artist": "Nathan Fake",
                "name": "HoursDaysMonthsSeasons",
                "album": "Providence"
            },
            {
                "artist": "Jake Chudnow",
                "name": "Shona",
                "album": "Shona"
            },
            {
                "artist": "Aperture Science Psychoacoustic Laboratories",
                "name": "Self Esteem Fund",
                "album": "Portal 2: Songs to Test By (Collectors Edition)"
            },
            {
                "artist": "Radiohead",
                "name": "Bloom (Jamie xx Rework)",
                "album": "TKOL RMX 1234567"
            },
            {
                "artist": "Nathan Fake",
                "name": "The Sky Was Pink - Holden Remix",
                "album": "The Sky Was Pink"
            },
            {
                "artist": "Alessandro Cortini",
                "name": "AMORE AMARO",
                "album": "BATTICUORE"
            },
            {
                "artist": "Stereoclip",
                "name": "Day One",
                "album": "Day One"
            },
            {
                "artist": "Aphex Twin",
                "name": "#3",
                "album": "Selected Ambient Works Volume II"
            },
            {
                "artist": "The Chemical Brothers",
                "name": "Another World",
                "album": "Further"
            },
            {
                "artist": "Rival Consoles",
                "name": "Helios",
                "album": "Sonne"
            },
            {
                "artist": "Nosaj Thing",
                "name": "Aquarium",
                "album": "Views/Octopus EP"
            },
            {
                "artist": "Plaid",
                "name": "Do Matter",
                "album": "The Digging Remedy"
            },
            {
                "artist": "Moderat",
                "name": "A New Error",
                "album": "Moderat"
            },
            {
                "artist": "Nils Frahm",
                "name": "Says",
                "album": "Spaces"
            },
            {
                "artist": "Anna Meredith",
                "name": "Honeyed Words",
                "album": "Varmints"
            },
            {
                "artist": "Nathan Fake",
                "name": "The Sky Was Pink - Icelandic Version",
                "album": "The Sky Was Pink"
            },
            {
                "artist": "Kiasmos",
                "name": "Thrown",
                "album": "Kiasmos"
            },
            {
                "artist": "Four Tet",
                "name": "Teenage Birdsong",
                "album": "Teenage Birdsong"
            },
            {
                "artist": "Clams Casino",
                "name": "Blast",
                "album": "32 Levels (Deluxe)"
            },
            {
                "artist": "Christian Löffler",
                "name": "Haul - Max Cooper Remix",
                "album": "Mare Reworks"
            },
            {
                "artist": "Four Tet",
                "name": "Two Thousand and Seventeen",
                "album": "New Energy"
            },
            {
                "artist": "AZEL PHARA",
                "name": "GREEN",
                "album": "GREEN"
            },
            {
                "artist": "Four Tet",
                "name": "Evening Side - Oneohtrix Point Never Edit",
                "album": "Evening Side (Oneohtrix Point Never Edit)"
            },
            {
                "artist": "Mssingno",
                "name": "Xe2",
                "album": "MssingNo EP"
            },
            {
                "artist": "M83",
                "name": "Another Wave From You",
                "album": "Hurry Up, We're Dreaming"
            },
            {
                "artist": "Donato Dozzy",
                "name": "Vaporware 05",
                "album": "Plays Bee Mask"
            },
            {
                "artist": "M83",
                "name": "Lower Your Eyelids To Die With the Sun",
                "album": "Before the Dawn Heals Us"
            },
            {
                "artist": "Moderat",
                "name": "Ghostmother",
                "album": "III (Deluxe Edition)"
            },
            {
                "artist": "Chrome Sparks",
                "name": "Send The Pain On",
                "album": "Sparks EP"
            },
            {
                "artist": "Jacques Greene",
                "name": "Serenity",
                "album": "Dawn Chorus"
            },
            {
                "artist": "Gil Scott-Heron",
                "name": "NY Is Killing Me",
                "album": "We're New Here"
            },
            {
                "artist": "Dye",
                "name": "Fantasy",
                "album": "Electro Classics"
            },
            {
                "artist": "Abul Mogard",
                "name": "Bound Universe",
                "album": "Circular Forms"
            },
            {
                "artist": "Caterina Barbieri",
                "name": "SOTRS",
                "album": "Patterns Of Consciousness"
            },
            {
                "artist": "Caterina Barbieri",
                "name": "Fantas",
                "album": "Ecstatic Computation"
            },
            {
                "artist": "Moderat",
                "name": "Seamonkey",
                "album": "Moderat (Deluxe Version)"
            },
            {
                "artist": "Joakim",
                "name": "Samurai (Meditation Tunnel Remix)",
                "album": "Remixes"
            },
            {
                "artist": "Colleen",
                "name": "Separating",
                "album": "A flame my love, a frequency"
            },
            {
                "artist": "Jake Chudnow",
                "name": "Keith",
                "album": "Tour De Traum XII"
            },
            {
                "artist": "･ ･－･ ･－ ･･･ ･ －･･",
                "name": "-- ・ -・・ ・ ・-・・ ・-",
                "album": "-- ・ -・・ ・ ・-・・ ・-"
            }
        ]
    }
]